xbasin/__init__.py
xbasin/_interpolation.py
xbasin/_remapping.py
xbasin/_stratification.py
xbasin/_stream_functions.py
xbasin/eos.py
xbasin/stratification.py
xbasin/stream_functions.py
xbasin/surface_flux.py
xbasin-0.0.5.dist-info/LICENSE
xbasin-0.0.5.dist-info/METADATA
xbasin-0.0.5.dist-info/WHEEL
xbasin-0.0.5.dist-info/top_level.txt
xbasin-0.0.5.dist-info/RECORD
