Metadata-Version: 2.1
Name: xbasin
Version: 0.0.5
Summary: TODO
Home-page: https://github.com/rcaneill/xbasin
Author: Romain Caneill
Author-email: romain.caneill@gu.se
License: MIT
Platform: UNKNOWN
Classifier: Development Status :: 3 - Alpha
Classifier: Programming Language :: Python
Classifier: Programming Language :: Python :: 3
Classifier: Intended Audience :: Science/Research
Classifier: License :: OSI Approved :: MIT License
Requires-Python: >=3.6
Requires-Dist: dask
Requires-Dist: numpy
Requires-Dist: xarray
